MANIFEST.in
README.rst
drifter.py
setup.py
virtualbox.py
docs/changes.rst
docs/conf.py
docs/index.rst
drifter.egg-info/PKG-INFO
drifter.egg-info/SOURCES.txt
drifter.egg-info/dependency_links.txt
drifter.egg-info/entry_points.txt
drifter.egg-info/requires.txt
drifter.egg-info/top_level.txt