Metadata-Version: 1.1
Name: drifter
Version: 0.0.2
Summary: VirtualBox control and documentation mechanism
Home-page: https://bitbucket.org/dundeemt/drifter
Author: Jeff Hinrichs
Author-email: jeffh@dundeemt.com
License: BSD
Download-URL: https://pypi.python.org/pypi/drifter
Keywords: VirtualBox Vagrant Development
Platform: any
Classifier: Development Status :: 4 - Beta
Classifier: License :: OSI Approved :: BSD License
Classifier: Programming Language :: Python
Classifier: Programming Language :: Python :: 2
Classifier: Programming Language :: Python :: 2.7
Classifier: Programming Language :: Python :: Implementation :: CPython
